Workbook
Name Alajuela: Listas!$C$3:$C$37
Name Cartago: Listas!$D$3:$D$37
Name Educación: 'Costos de Reposicion'!$V$10:$V$18
Name escenarios: Listas!$J$3:$J$5
Name Guanacaste: Listas!$E$3:$E$37
Name Heredia: Listas!$F$3:$F$37
Name Interv_Educación: Intervenciones!$B$12:$B$14
Name Interv_Residencial: Intervenciones!$B$15:$B$17
Name Interv_Salud: Intervenciones!$B$18:$B$20
Name Interv_Transporte: Intervenciones!$B$21:$B$23
Name intervensiones: Listas!#REF!
Name Limón: Listas!$G$3:$G$37
Name Provincias: Listas!$B$3:$B$9
Name Puntarenas: Listas!$H$3:$H$37
Name Residencial: 'Costos de Reposicion'!$W$10:$W$18
Name Salud: 'Costos de Reposicion'!$X$10:$X$18
Name San_Jose: Listas!$I$3:$I$37
Name Transporte: 'Costos de Reposicion'!$Y$10:$Y$18

Sheet Instrucciones
A7: Herramienta de Evaluación de Costo-Beneficio de Intervenciones para la Reducción de Riesgo Catastrófico
A9: Hoja de Instrucciones y Suposiciones Metodológicas
A11: Objetivo de la Herramienta
A13: Esta calculadora ha sido diseñada como un instrumento de apoyo a la toma de decisiones para priorizar inversiones de reducción de riesgo en infraestructura física (vertical y vial) en Costa Rica. Su propósito principal es trascender la evaluación puramente financiera, integrando métricas de riesgo de desastres y sostenibilidad ambiental.
A15: La herramienta estima la Pérdida Anual Promedio (AAL) basándose en el perfil estadístico probabilista de cada Cantón (utilizando datos del GRAF) y realiza un Análisis Costo-Beneficio (CBA) integral. Esto permite comparar la rentabilidad de una intervención preventiva (reforzamiento, reconstrucción, mejoras) frente al costo futuro probable de los desastres y el impacto ambiental de la reconstrucción.
A17: ¿Qué tipo de estructuras evalúa esta herramienta? El modelo está calibrado exclusivamente para las siguientes tipologías, basándose en la información disponible en el GRAF:
A19: 1. Infraestructura Vertical (Edificaciones):
A20: Educación: Centros educativos, aulas, comedores y gimnasios escolares.
A21: Salud: EBAIS, clínicas, áreas de salud y hospitales.
A22: Residencial: Viviendas individuales, proyectos de bono familiar y reasentamientos.
A24: 2. Infraestructura Vial (Transporte):
A25: Red Vial: Carreteras (asfalto/concreto), caminos vecinales y sus sistemas de drenaje.
... A93: Precio Social del Carbono: $40 USD por tonelada métrica. Este valor es ajustable en la hoja "Listas" y representa el costo económico del daño ambiental evitado, sumándose al beneficio financiero del proyecto.

Sheet Principal
A2: Herramienta de Evaluación de Costo-Beneficio de Intervenciones para la Reducción de Riesgo Catastrófico
A5: Input de Portafolio
C7: Campo editable
B9: ID | C9: Proyecto | D9: Provincia | E9: Cantón | F9: Sector | G9: Costo Reposición | H9: Sample Size | I9: AALR Promedio | J9: Desv. Estándar | K9: AALR Min | L9: Vulnerabilidad | M9: AALR Ref. | N9: AAL Ref. | O9: Intervención | P9: Costo Intervención | Q9: AALR Reducido | R9: AAL Reducido | S9: Ahorro anual | T9: Vida útil (años) | U9: Tasa descuento | V9: VPN | W9: ton CO2 ahorro | X9: Ahorro social | Y9: Beneficio/Costo | AI9: Resumen por Provincia | AJ9: Costo Reposición ($) | AK9: Inversión ($) | AL9: Ahorro ($) | AN9: Resumen por Sector | AO9: Costo Reposición ($) | AP9: Inversión ($)
B10: 43754-EP-FNE-014 | C10: Escuela Colorado | D10: Puntarenas | E10: Corredores | F10: Educación | G10: 1440000 | H10: =IF(D10="","-", INDEX(asset_counts_canton!$B$2:$G$83,MATCH(Principal!E10,asset_counts_canton!$A$2:$A$83,0),MATCH(Principal!F10,asset_counts_canton!$B$1:$G$1,0))) -> 91 | I10: =IF(D10="","-", INDEX(average_aalr_tot_canton!$B$2:$G$83,MATCH(E10,average_aalr_tot_canton!$A$2:$A$83,0),MATCH(F10,average_aalr_tot_canton!$B$1:$G$1,0))) -> 0.014478022 | J10: =IF(D10="","-", INDEX(std_dev_aalr_tot_canton!$B$2:$G$83,MATCH(E10,std_dev_aalr_tot_canton!$A$2:$A$83,0),MATCH(F10,std_dev_aalr_tot_canton!$B$1:$G$1,0))) -> 0.0043378387 | K10: =IF(D10="","-", INDEX(min_aalr_tot_canton!$B$2:$G$83,MATCH(E10,min_aalr_tot_canton!$A$2:$A$83,0),MATCH(F10,min_aalr_tot_canton!$B$1:$G$1,0))) -> 0.0103 | L10: Alta | M10: =IF(D10="","-", IF(L10="Promedio",I10, IF(L10="Alta",(I10+2*J10),AVERAGE(K10,I10)))) -> 0.023153699 | N10: =IF(D10="","-", M10*G10) -> 33341.327 | O10: Mantenimiento Correctivo Menor | P10: =IF(D10="","-", Principal!G10*VLOOKUP(Principal!O10,Intervenciones!$B$12:$E$23,3,FALSE)) -> 72000 | Q10: =IF(D10="","-", MAX(0.001,N10/G10*(1-VLOOKUP(O10,Intervenciones!$B$12:$E$23,4,FALSE)))) -> 0.01852296 | R10: =IF(D10="","-", Q10*G10) -> 26673.062 | S10: =IF(D10="","-",N10-R10) -> 6668.2654 | T10: 50 | U10: 0.04 | V10: =IF(D10="","-", PV(U10,T10,-(N10-R10))) -> 143248.91 | W10: =IF(D10="","-", PV(Listas!$K$3,T10,-(N10-R10)*Listas!$L$3)/1000) -> 78.761404 | X10: =IF(D10="","-", W10*Listas!$M$3) -> 3150.4562 | Y10: =IF(D10="","-", (V10+X10)/P10) -> 2.0333245 | AI10: Alajuela | AJ10: =SUMIF(D:D, AI10, G:G) -> 60000000 | AK10: =SUMIF(D:D, AI10, P:P) -> 7500000 | AL10: =SUMIF(D:D, AI10, V:V) -> 1388084.3 | AN10: Educación | AO10: =SUMIF(F:F, AN10, G:G) -> 10040000 | AP10: =SUMIF(F:F, AN10, P:P) -> 5407000
B11: 43752-EP-FNE-021 | C11: Escuela Mercedes | D11: San_Jose | E11: Aserrí | F11: Educación | G11: 3000000 | H11: =IF(D11="","-", INDEX(asset_counts_canton!$B$2:$G$83,MATCH(Principal!E11,asset_counts_canton!$A$2:$A$83,0),MATCH(Principal!F11,asset_counts_canton!$B$1:$G$1,0))) -> 33 | I11: =IF(D11="","-", INDEX(average_aalr_tot_canton!$B$2:$G$83,MATCH(E11,average_aalr_tot_canton!$A$2:$A$83,0),MATCH(F11,average_aalr_tot_canton!$B$1:$G$1,0))) -> 0.015339394 | J11: =IF(D11="","-", INDEX(std_dev_aalr_tot_canton!$B$2:$G$83,MATCH(E11,std_dev_aalr_tot_canton!$A$2:$A$83,0),MATCH(F11,std_dev_aalr_tot_canton!$B$1:$G$1,0))) -> 0.0051124199 | K11: =IF(D11="","-", INDEX(min_aalr_tot_canton!$B$2:$G$83,MATCH(E11,min_aalr_tot_canton!$A$2:$A$83,0),MATCH(F11,min_aalr_tot_canton!$B$1:$G$1,0))) -> 0.0121 | L11: Alta | M11: =IF(D11="","-", IF(L11="Promedio",I11, IF(L11="Alta",(I11+2*J11),AVERAGE(K11,I11)))) -> 0.025564234 | N11: =IF(D11="","-", M11*G11) -> 76692.701 | O11: Reforzamiento Estructural (Retrofitting) | P11: =IF(D11="","-", Principal!G11*VLOOKUP(Principal!O11,Intervenciones!$B$12:$E$23,3,FALSE)) -> 1050000 | Q11: =IF(D11="","-", MAX(0.001,N11/G11*(1-VLOOKUP(O11,Intervenciones!$B$12:$E$23,4,FALSE)))) -> 0.0076692701 | R11: =IF(D11="","-", Q11*G11) -> 23007.81 | S11: =IF(D11="","-",N11-R11) -> 53684.891 | T11: 50 | U11: 0.04 | V11: =IF(D11="","-", PV(U11,T11,-(N11-R11))) -> 1153268.7 | W11: =IF(D11="","-", PV(Listas!$K$3,T11,-(N11-R11)*Listas!$L$3)/1000) -> 634.09254 | X11: =IF(D11="","-", W11*Listas!$M$3) -> 25363.702 | Y11: =IF(D11="","-", (V11+X11)/P11) -> 1.1225071 | AI11: Cartago | AJ11: =SUMIF(D:D, AI11, G:G) -> 0 | AK11: =SUMIF(D:D, AI11, P:P) -> 0 | AL11: =SUMIF(D:D, AI11, V:V) -> 0 | AN11: Residencial | AO11: =SUMIF(F:F, AN11, G:G) -> 0 | AP11: =SUMIF(F:F, AN11, P:P) -> 0
B12: CONAVI-CA-001 | C12: Carreteras San Carlos | D12: Alajuela | E12: San_Carlos | F12: Transporte | G12: 30000000 | H12: =IF(D12="","-", INDEX(asset_counts_canton!$B$2:$G$83,MATCH(Principal!E12,asset_counts_canton!$A$2:$A$83,0),MATCH(Principal!F12,asset_counts_canton!$B$1:$G$1,0))) -> 65 | I12: =IF(D12="","-", INDEX(average_aalr_tot_canton!$B$2:$G$83,MATCH(E12,average_aalr_tot_canton!$A$2:$A$83,0),MATCH(F12,average_aalr_tot_canton!$B$1:$G$1,0))) -> 0.0034111111 | J12: =IF(D12="","-", INDEX(std_dev_aalr_tot_canton!$B$2:$G$83,MATCH(E12,std_dev_aalr_tot_canton!$A$2:$A$83,0),MATCH(F12,std_dev_aalr_tot_canton!$B$1:$G$1,0))) -> 0.0023691642 | K12: =IF(D12="","-", INDEX(min_aalr_tot_canton!$B$2:$G$83,MATCH(E12,min_aalr_tot_canton!$A$2:$A$83,0),MATCH(F12,min_aalr_tot_canton!$B$1:$G$1,0))) -> 0.0009 | L12: Alta | M12: =IF(D12="","-", IF(L12="Promedio",I12, IF(L12="Alta",(I12+2*J12),AVERAGE(K12,I12)))) -> 0.0081494395 | N12: =IF(D12="","-", M12*G12) -> 244483.19 | O12: Estabilización de Taludes | P12: =IF(D12="","-", Principal!G12*VLOOKUP(Principal!O12,Intervenciones!$B$12:$E$23,3,FALSE)) -> 4500000 | Q12: =IF(D12="","-", MAX(0.001,N12/G12*(1-VLOOKUP(O12,Intervenciones!$B$12:$E$23,4,FALSE)))) -> 0.0048896637 | R12: =IF(D12="","-", Q12*G12) -> 146689.91 | S12: =IF(D12="","-",N12-R12) -> 97793.274 | T12: 10 | U12: 0.04 | V12: =IF(D12="","-", PV(U12,T12,-(N12-R12))) -> 793191.06 | W12: =IF(D12="","-", PV(Listas!$K$3,T12,-(N12-R12)*Listas!$L$3)/1000) -> 647.1236 | X12: =IF(D12="","-", W12*Listas!$M$3) -> 25884.944 | Y12: =IF(D12="","-", (V12+X12)/P12) -> 0.18201689 | AI12: Guanacaste | AJ12: =SUMIF(D:D, AI12, G:G) -> 3100000 | AK12: =SUMIF(D:D, AI12, P:P) -> 3410000 | AL12: =SUMIF(D:D, AI12, V:V) -> 685234.16 | AN12: Salud | AO12: =SUMIF(F:F, AN12, G:G) -> 4000000 | AP12: =SUMIF(F:F, AN12, P:P) -> 1600000
B13: CONAVI-CA-001 | C13: Carreteras San Carlos | D13: Alajuela | E13: San_Carlos | F13: Transporte | G13: 30000000 | H13: =IF(D13="","-", INDEX(asset_counts_canton!$B$2:$G$83,MATCH(Principal!E13,asset_counts_canton!$A$2:$A$83,0),MATCH(Principal!F13,asset_counts_canton!$B$1:$G$1,0))) -> 65 | I13: =IF(D13="","-", INDEX(average_aalr_tot_canton!$B$2:$G$83,MATCH(E13,average_aalr_tot_canton!$A$2:$A$83,0),MATCH(F13,average_aalr_tot_canton!$B$1:$G$1,0))) -> 0.0034111111 | J13: =IF(D13="","-", INDEX(std_dev_aalr_tot_canton!$B$2:$G$83,MATCH(E13,std_dev_aalr_tot_canton!$A$2:$A$83,0),MATCH(F13,std_dev_aalr_tot_canton!$B$1:$G$1,0))) -> 0.0023691642 | K13: =IF(D13="","-", INDEX(min_aalr_tot_canton!$B$2:$G$83,MATCH(E13,min_aalr_tot_canton!$A$2:$A$83,0),MATCH(F13,min_aalr_tot_canton!$B$1:$G$1,0))) -> 0.0009 | L13: Alta | M13: =IF(D13="","-", IF(L13="Promedio",I13, IF(L13="Alta",(I13+2*J13),AVERAGE(K13,I13)))) -> 0.0081494395 | N13: =IF(D13="","-", M13*G13) -> 244483.19 | O13: Mejora de Sistemas de Drenaje | P13: =IF(D13="","-", Principal!G13*VLOOKUP(Principal!O13,Intervenciones!$B$12:$E$23,3,FALSE)) -> 3000000 | Q13: =IF(D13="","-", MAX(0.001,N13/G13*(1-VLOOKUP(O13,Intervenciones!$B$12:$E$23,4,FALSE)))) -> 0.0057046077 | R13: =IF(D13="","-", Q13*G13) -> 171138.23 | S13: =IF(D13="","-",N13-R13) -> 73344.956 | T13: 10 | U13: 0.04 | V13: =IF(D13="","-", PV(U13,T13,-(N13-R13))) -> 594893.29 | W13: =IF(D13="","-", PV(Listas!$K$3,T13,-(N13-R13)*Listas!$L$3)/1000) -> 485.3427 | X13: =IF(D13="","-", W13*Listas!$M$3) -> 19413.708 | Y13: =IF(D13="","-", (V13+X13)/P13) -> 0.204769 | AI13: Heredia | AJ13: =SUMIF(D:D, AI13, G:G) -> 4000000 | AK13: =SUMIF(D:D, AI13, P:P) -> 1600000 | AL13: =SUMIF(D:D, AI13, V:V) -> 5829642.2 | AN13: Transporte | AO13: =SUMIF(F:F, AN13, G:G) -> 60000000 | AP13: =SUMIF(F:F, AN13, P:P) -> 7500000
B14: 43754-EP-FNE-037 | C14: Liceo Finca Alajuela | D14: Puntarenas | E14: Osa | F14: Educación | G14: 2500000 | H14: =IF(D14="","-", INDEX(asset_counts_canton!$B$2:$G$83,MATCH(Principal!E14,asset_counts_canton!$A$2:$A$83,0),MATCH(Principal!F14,asset_counts_canton!$B$1:$G$1,0))) -> 101 | I14: =IF(D14="","-", INDEX(average_aalr_tot_canton!$B$2:$G$83,MATCH(E14,average_aalr_tot_canton!$A$2:$A$83,0),MATCH(F14,average_aalr_tot_canton!$B$1:$G$1,0))) -> 0.013990099 | J14: =IF(D14="","-", INDEX(std_dev_aalr_tot_canton!$B$2:$G$83,MATCH(E14,std_dev_aalr_tot_canton!$A$2:$A$83,0),MATCH(F14,std_dev_aalr_tot_canton!$B$1:$G$1,0))) -> 0.0037836888 | K14: =IF(D14="","-", INDEX(min_aalr_tot_canton!$B$2:$G$83,MATCH(E14,min_aalr_tot_canton!$A$2:$A$83,0),MATCH(F14,min_aalr_tot_canton!$B$1:$G$1,0))) -> 0.0111 | L14: Alta | M14: =IF(D14="","-", IF(L14="Promedio",I14, IF(L14="Alta",(I14+2*J14),AVERAGE(K14,I14)))) -> 0.021557477 | N14: =IF(D14="","-", M14*G14) -> 53893.692 | O14: Reforzamiento Estructural (Retrofitting) | P14: =IF(D14="","-", Principal!G14*VLOOKUP(Principal!O14,Intervenciones!$B$12:$E$23,3,FALSE)) -> 875000 | Q14: =IF(D14="","-", MAX(0.001,N14/G14*(1-VLOOKUP(O14,Intervenciones!$B$12:$E$23,4,FALSE)))) -> 0.006467243 | R14: =IF(D14="","-", Q14*G14) -> 16168.107 | S14: =IF(D14="","-",N14-R14) -> 37725.584 | T14: 50 | U14: 0.04 | V14: =IF(D14="","-", PV(U14,T14,-(N14-R14))) -> 810427.96 | W14: =IF(D14="","-", PV(Listas!$K$3,T14,-(N14-R14)*Listas!$L$3)/1000) -> 445.59114 | X14: =IF(D14="","-", W14*Listas!$M$3) -> 17823.646 | Y14: =IF(D14="","-", (V14+X14)/P14) -> 0.94657327 | AI14: Limón | AJ14: =SUMIF(D:D, AI14, G:G) -> 0 | AK14: =SUMIF(D:D, AI14, P:P) -> 0 | AL14: =SUMIF(D:D, AI14, V:V) -> 0
B15: MEP-CE-034 | C15: Centro Educativo Victoriano Mena | D15: Guanacaste | E15: Hojancha | F15: Educación | G15: 3100000 | H15: =IF(D15="","-", INDEX(asset_counts_canton!$B$2:$G$83,MATCH(Principal!E15,asset_counts_canton!$A$2:$A$83,0),MATCH(Principal!F15,asset_counts_canton!$B$1:$G$1,0))) -> 22 | I15: =IF(D15="","-", INDEX(average_aalr_tot_canton!$B$2:$G$83,MATCH(E15,average_aalr_tot_canton!$A$2:$A$83,0),MATCH(F15,average_aalr_tot_canton!$B$1:$G$1,0))) -> 0.010745455 | J15: =IF(D15="","-", INDEX(std_dev_aalr_tot_canton!$B$2:$G$83,MATCH(E15,std_dev_aalr_tot_canton!$A$2:$A$83,0),MATCH(F15,std_dev_aalr_tot_canton!$B$1:$G$1,0))) -> 0.00027207715 | K15: =IF(D15="","-", INDEX(min_aalr_tot_canton!$B$2:$G$83,MATCH(E15,min_aalr_tot_canton!$A$2:$A$83,0),MATCH(F15,min_aalr_tot_canton!$B$1:$G$1,0))) -> 0.0101 | L15: Alta | M15: =IF(D15="","-", IF(L15="Promedio",I15, IF(L15="Alta",(I15+2*J15),AVERAGE(K15,I15)))) -> 0.011289609 | N15: =IF(D15="","-", M15*G15) -> 34997.787 | O15: Reconstrucción Total (Código Actual) | P15: =IF(D15="","-", Principal!G15*VLOOKUP(Principal!O15,Intervenciones!$B$12:$E$23,3,FALSE)) -> 3410000 | Q15: =IF(D15="","-", MAX(0.001,N15/G15*(1-VLOOKUP(O15,Intervenciones!$B$12:$E$23,4,FALSE)))) -> 0.001 | R15: =IF(D15="","-", Q15*G15) -> 3100 | S15: =IF(D15="","-",N15-R15) -> 31897.787 | T15: 50 | U15: 0.04 | V15: =IF(D15="","-", PV(U15,T15,-(N15-R15))) -> 685234.16 | W15: =IF(D15="","-", PV(Listas!$K$3,T15,-(N15-R15)*Listas!$L$3)/1000) -> 376.75683 | X15: =IF(D15="","-", W15*Listas!$M$3) -> 15070.273 | Y15: =IF(D15="","-", (V15+X15)/P15) -> 0.20536787 | AI15: Puntarenas | AJ15: =SUMIF(D:D, AI15, G:G) -> 3940000 | AK15: =SUMIF(D:D, AI15, P:P) -> 947000 | AL15: =SUMIF(D:D, AI15, V:V) -> 953676.87
B16: 7 | C16: Ejemplo | D16: Heredia | E16: San_Pablo | F16: Salud | G16: 4000000 | H16: =IF(D16="","-", INDEX(asset_counts_canton!$B$2:$G$83,MATCH(Principal!E16,asset_counts_canton!$A$2:$A$83,0),MATCH(Principal!F16,asset_counts_canton!$B$1:$G$1,0))) -> 4 | I16: =IF(D16="","-", INDEX(average_aalr_tot_canton!$B$2:$G$83,MATCH(E16,average_aalr_tot_canton!$A$2:$A$83,0),MATCH(F16,average_aalr_tot_canton!$B$1:$G$1,0))) -> 0.035175 | J16: =IF(D16="","-", INDEX(std_dev_aalr_tot_canton!$B$2:$G$83,MATCH(E16,std_dev_aalr_tot_canton!$A$2:$A$83,0),MATCH(F16,std_dev_aalr_tot_canton!$B$1:$G$1,0))) -> 0.022320002 | K16: =IF(D16="","-", INDEX(min_aalr_tot_canton!$B$2:$G$83,MATCH(E16,min_aalr_tot_canton!$A$2:$A$83,0),MATCH(F16,min_aalr_tot_canton!$B$1:$G$1,0))) -> 0.0017 | L16: Alta | M16: =IF(D16="","-", IF(L16="Promedio",I16, IF(L16="Alta",(I16+2*J16),AVERAGE(K16,I16)))) -> 0.079815004 | N16: =IF(D16="","-", M16*G16) -> 319260.02 | O16: Reforzamiento Estructural Integral | P16: =IF(D16="","-", Principal!G16*VLOOKUP(Principal!O16,Intervenciones!$B$12:$E$23,3,FALSE)) -> 1600000 | Q16: =IF(D16="","-", MAX(0.001,N16/G16*(1-VLOOKUP(O16,Intervenciones!$B$12:$E$23,4,FALSE)))) -> 0.011972251 | R16: =IF(D16="","-", Q16*G16) -> 47889.003 | S16: =IF(D16="","-",N16-R16) -> 271371.02 | T16: 50 | U16: 0.04 | V16: =IF(D16="","-", PV(U16,T16,-(N16-R16))) -> 5829642.2 | W16: =IF(D16="","-", PV(Listas!$K$3,T16,-(N16-R16)*Listas!$L$3)/1000) -> 3205.2657 | X16: =IF(D16="","-", W16*Listas!$M$3) -> 128210.63 | Y16: =IF(D16="","-", (V16+X16)/P16) -> 3.723658 | AI16: San_Jose | AJ16: =SUMIF(D:D, AI16, G:G) -> 3000000 | AK16: =SUMIF(D:D, AI16, P:P) -> 1050000 | AL16: =SUMIF(D:D, AI16, V:V) -> 1153268.7
B17: 8 | H17: =IF(D17="","-", INDEX(asset_counts_canton!$B$2:$G$83,MATCH(Principal!E17,asset_counts_canton!$A$2:$A$83,0),MATCH(Principal!F17,asset_counts_canton!$B$1:$G$1,0))) -> - | I17: =IF(D17="","-", INDEX(average_aalr_tot_canton!$B$2:$G$83,MATCH(E17,average_aalr_tot_canton!$A$2:$A$83,0),MATCH(F17,average_aalr_tot_canton!$B$1:$G$1,0))) -> - | J17: =IF(D17="","-", INDEX(std_dev_aalr_tot_canton!$B$2:$G$83,MATCH(E17,std_dev_aalr_tot_canton!$A$2:$A$83,0),MATCH(F17,std_dev_aalr_tot_canton!$B$1:$G$1,0))) -> - | K17: =IF(D17="","-", INDEX(min_aalr_tot_canton!$B$2:$G$83,MATCH(E17,min_aalr_tot_canton!$A$2:$A$83,0),MATCH(F17,min_aalr_tot_canton!$B$1:$G$1,0))) -> - | M17: =IF(D17="","-", IF(L17="Promedio",I17, IF(L17="Alta",(I17+2*J17),AVERAGE(K17,I17)))) -> - | N17: =IF(D17="","-", M17*G17) -> - | P17: =IF(D17="","-", Principal!G17*VLOOKUP(Principal!O17,Intervenciones!$B$12:$E$23,3,FALSE)) -> - | Q17: =IF(D17="","-", MAX(0.001,N17/G17*(1-VLOOKUP(O17,Intervenciones!$B$12:$E$23,4,FALSE)))) -> - | R17: =IF(D17="","-", Q17*G17) -> - | S17: =IF(D17="","-",N17-R17) -> - | V17: =IF(D17="","-", PV(U17,T17,-(N17-R17))) -> - | W17: =IF(D17="","-", PV(Listas!$K$3,T17,-(N17-R17)*Listas!$L$3)/1000) -> - | X17: =IF(D17="","-", W17*Listas!$M$3) -> - | Y17: =IF(D17="","-", (V17+X17)/P17) -> -
B18: 9 | H18: =IF(D18="","-", INDEX(asset_counts_canton!$B$2:$G$83,MATCH(Principal!E18,asset_counts_canton!$A$2:$A$83,0),MATCH(Principal!F18,asset_counts_canton!$B$1:$G$1,0))) -> - | I18: =IF(D18="","-", INDEX(average_aalr_tot_canton!$B$2:$G$83,MATCH(E18,average_aalr_tot_canton!$A$2:$A$83,0),MATCH(F18,average_aalr_tot_canton!$B$1:$G$1,0))) -> - | J18: =IF(D18="","-", INDEX(std_dev_aalr_tot_canton!$B$2:$G$83,MATCH(E18,std_dev_aalr_tot_canton!$A$2:$A$83,0),MATCH(F18,std_dev_aalr_tot_canton!$B$1:$G$1,0))) -> - | K18: =IF(D18="","-", INDEX(min_aalr_tot_canton!$B$2:$G$83,MATCH(E18,min_aalr_tot_canton!$A$2:$A$83,0),MATCH(F18,min_aalr_tot_canton!$B$1:$G$1,0))) -> - | M18: =IF(D18="","-", IF(L18="Promedio",I18, IF(L18="Alta",(I18+2*J18),AVERAGE(K18,I18)))) -> - | N18: =IF(D18="","-", M18*G18) -> - | P18: =IF(D18="","-", Principal!G18*VLOOKUP(Principal!O18,Intervenciones!$B$12:$E$23,3,FALSE)) -> - | Q18: =IF(D18="","-", MAX(0.001,N18/G18*(1-VLOOKUP(O18,Intervenciones!$B$12:$E$23,4,FALSE)))) -> - | R18: =IF(D18="","-", Q18*G18) -> - | S18: =IF(D18="","-",N18-R18) -> - | V18: =IF(D18="","-", PV(U18,T18,-(N18-R18))) -> - | W18: =IF(D18="","-", PV(Listas!$K$3,T18,-(N18-R18)*Listas!$L$3)/1000) -> - | X18: =IF(D18="","-", W18*Listas!$M$3) -> - | Y18: =IF(D18="","-", (V18+X18)/P18) -> -
B19: 10 | H19: =IF(D19="","-", INDEX(asset_counts_canton!$B$2:$G$83,MATCH(Principal!E19,asset_counts_canton!$A$2:$A$83,0),MATCH(Principal!F19,asset_counts_canton!$B$1:$G$1,0))) -> - | I19: =IF(D19="","-", INDEX(average_aalr_tot_canton!$B$2:$G$83,MATCH(E19,average_aalr_tot_canton!$A$2:$A$83,0),MATCH(F19,average_aalr_tot_canton!$B$1:$G$1,0))) -> - | J19: =IF(D19="","-", INDEX(std_dev_aalr_tot_canton!$B$2:$G$83,MATCH(E19,std_dev_aalr_tot_canton!$A$2:$A$83,0),MATCH(F19,std_dev_aalr_tot_canton!$B$1:$G$1,0))) -> - | K19: =IF(D19="","-", INDEX(min_aalr_tot_canton!$B$2:$G$83,MATCH(E19,min_aalr_tot_canton!$A$2:$A$83,0),MATCH(F19,min_aalr_tot_canton!$B$1:$G$1,0))) -> - | M19: =IF(D19="","-", IF(L19="Promedio",I19, IF(L19="Alta",(I19+2*J19),AVERAGE(K19,I19)))) -> - | N19: =IF(D19="","-", M19*G19) -> - | P19: =IF(D19="","-", Principal!G19*VLOOKUP(Principal!O19,Intervenciones!$B$12:$E$23,3,FALSE)) -> - | Q19: =IF(D19="","-", MAX(0.001,N19/G19*(1-VLOOKUP(O19,Intervenciones!$B$12:$E$23,4,FALSE)))) -> - | R19: =IF(D19="","-", Q19*G19) -> - | S19: =IF(D19="","-",N19-R19) -> - | V19: =IF(D19="","-", PV(U19,T19,-(N19-R19))) -> - | W19: =IF(D19="","-", PV(Listas!$K$3,T19,-(N19-R19)*Listas!$L$3)/1000) -> - | X19: =IF(D19="","-", W19*Listas!$M$3) -> - | Y19: =IF(D19="","-", (V19+X19)/P19) -> -
A22: Resumen de Resultados
B24: Costo total del inventario | D24: =SUM(G10:G19) -> 74040000
B25: Inversión total | D25: =SUM(P10:P19) -> 14507000
B26: Pérdidas anuales base | D26: =SUM(N10:N19) -> 1007151.9
B27: Ahorro anual estimado | D27: =D26-SUM(R10:R19) -> 572485.77
B28: Beneficio social CO2 | D28: =SUM(X10:X19) -> 234917.36
B29: Beneficio total | D29: =SUM(V10:V19)+D28 -> 10244824
B30: Beneficio/Costo total | D30: =D29/D25 -> 0.70619864
A51: Referencias
A52: Datos estadísticos de pérdidas | D52: Marco Global de Evaluación del Riesgo (GRAF), CNE UNDRR (2023)
A53: Beneficios sociales | D53: Precios Sociales en Costa Rica, MIDEPLAN (2025)

Sheet Costos de Reposicion
A2: Herramienta de Evaluación de Costo-Beneficio de Intervenciones para la Reducción de Riesgo Catastrófico
A6: Costos de Referencia
C8: Campo editable
U9: - | V9: Educación | W9: Residencial | X9: Salud | Y9: Transporte | AB9: Sectores | AC9: Sector | AD9: Tipología | AE9: Unidad | AF9: Costo_unit_USD
A10: ID | B10: Sector | C10: Tipología | D10: Unidad de Medida | E10: Costo Unitario | F10: Cantidad | G10: Costo de Reposición | U10: - | V10: Centro_educativo_rural | W10: Residencial_baja | X10: EBAIS | Y10: Carretera_asfalto_2carriles | AB10: Educación | AC10: Residencial | AD10: Residencial_baja | AE10: m2 | AF10: 600
A11: 1 | B11: Educación | C11: Centro_educativo_urbano | D11: =IF(B11="-","-",VLOOKUP(C11,$AD$10:$AF$25,2,FALSE)) -> m2 | E11: =IF(B11="-","-",VLOOKUP(C11,$AD$10:$AF$25,3,FALSE)) -> 1150 | F11: 4000 | G11: =IF(F11="-","-",E11*F11) -> 4600000 | V11: Centro_educativo_urbano | W11: Residencial_media | X11: Clinica | Y11: Carretera_asfalto_3carriles | AB11: Residencial | AC11: Residencial | AD11: Residencial_media | AE11: m2 | AF11: 850
A12: 2 | B12: Educación | C12: Centro_educativo_rural | D12: =IF(B12="-","-",VLOOKUP(C12,$AD$10:$AF$25,2,FALSE)) -> m2 | E12: =IF(B12="-","-",VLOOKUP(C12,$AD$10:$AF$25,3,FALSE)) -> 900 | F12: 1600 | G12: =IF(F12="-","-",E12*F12) -> 1440000 | W12: Residencial_alta | X12: Hospital | Y12: Carretera_asfalto_4carriles | AB12: Salud | AC12: Residencial | AD12: Residencial_alta | AE12: m2 | AF12: 1050
A13: 3 | B13: Transporte | C13: Carretera_asfalto_2carriles | D13: =IF(B13="-","-",VLOOKUP(C13,$AD$10:$AF$25,2,FALSE)) -> km | E13: =IF(B13="-","-",VLOOKUP(C13,$AD$10:$AF$25,3,FALSE)) -> 1200000 | F13: 8 | G13: =IF(F13="-","-",E13*F13) -> 9600000 | Y13: Carretera_concreto_2carriles | AB13: Transporte | AC13: Educación | AD13: Centro_educativo_rural | AE13: m2 | AF13: 900
A14: 4 | B14: Salud | C14: EBAIS | D14: =IF(B14="-","-",VLOOKUP(C14,$AD$10:$AF$25,2,FALSE)) -> m2 | E14: =IF(B14="-","-",VLOOKUP(C14,$AD$10:$AF$25,3,FALSE)) -> 1100 | F14: 400 | G14: =IF(F14="-","-",E14*F14) -> 440000 | Y14: Carretera_concreto_3carriles | AC14: Educación | AD14: Centro_educativo_urbano | AE14: m2 | AF14: 1150
A15: 5 | B15: Residencial | C15: Residencial_baja | D15: =IF(B15="-","-",VLOOKUP(C15,$AD$10:$AF$25,2,FALSE)) -> m2 | E15: =IF(B15="-","-",VLOOKUP(C15,$AD$10:$AF$25,3,FALSE)) -> 600 | F15: 200 | G15: =IF(F15="-","-",E15*F15) -> 120000 | Y15: Carretera_concreto_4carriles | AC15: Salud | AD15: EBAIS | AE15: m2 | AF15: 1100
A16: 6 | B16: Educación | C16: Centro_educativo_rural | D16: =IF(B16="-","-",VLOOKUP(C16,$AD$10:$AF$25,2,FALSE)) -> m2 | E16: =IF(B16="-","-",VLOOKUP(C16,$AD$10:$AF$25,3,FALSE)) -> 900 | F16: 2300 | G16: =IF(F16="-","-",E16*F16) -> 2070000 | Y16: Camino_lastre | AC16: Salud | AD16: Clinica | AE16: m2 | AF16: 1500
A17: 7 | B17: Educación | C17: Centro_educativo_rural | D17: =IF(B17="-","-",VLOOKUP(C17,$AD$10:$AF$25,2,FALSE)) -> m2 | E17: =IF(B17="-","-",VLOOKUP(C17,$AD$10:$AF$25,3,FALSE)) -> 900 | F17: 3000 | G17: =IF(F17="-","-",E17*F17) -> 2700000 | AC17: Salud | AD17: Hospital | AE17: m2 | AF17: 2400
A18: 8 | B18: Salud | C18: Clinica | D18: =IF(B18="-","-",VLOOKUP(C18,$AD$10:$AF$25,2,FALSE)) -> m2 | E18: =IF(B18="-","-",VLOOKUP(C18,$AD$10:$AF$25,3,FALSE)) -> 1500 | F18: 10000 | G18: =IF(F18="-","-",E18*F18) -> 15000000 | AC18: Transporte | AD18: Carretera_asfalto_2carriles | AE18: km | AF18: 1200000
A19: 9 | B19: - | D19: =IF(B19="-","-",VLOOKUP(C19,$AD$10:$AF$25,2,FALSE)) -> - | E19: =IF(B19="-","-",VLOOKUP(C19,$AD$10:$AF$25,3,FALSE)) -> - | F19: - | G19: =IF(F19="-","-",E19*F19) -> - | AC19: Transporte | AD19: Carretera_asfalto_3carriles | AE19: km | AF19: 1800000
A20: 10 | B20: - | D20: =IF(B20="-","-",VLOOKUP(C20,$AD$10:$AF$25,2,FALSE)) -> - | E20: =IF(B20="-","-",VLOOKUP(C20,$AD$10:$AF$25,3,FALSE)) -> - | F20: - | G20: =IF(F20="-","-",E20*F20) -> - | AC20: Transporte | AD20: Carretera_asfalto_4carriles | AE20: km | AF20: 2400000
AC21: Transporte | AD21: Carretera_concreto_2carriles | AE21: km | AF21: 1600000
AC22: Transporte | AD22: Carretera_concreto_3carriles | AE22: km | AF22: 2400000
A23: Notas | B23: Estos costos son de referencia, basados en valores típicos de construcción en Costa Rica para el 2025 | AC23: Transporte | AD23: Carretera_concreto_4carriles | AE23: km | AF23: 3200000
AC24: Transporte | AD24: Camino_lastre | AE24: km | AF24: 200000
A25: Referencias de Costos de Reposición | AC25: - | AD25: - | AE25: - | AF25: -
A27: Los valores unitarios sugeridos han sido estimados triangulando información de las siguientes fuentes oficiales en Costa Rica:
A29: 1. Edificaciones (Educación, Salud, Residencial):
A30: CFIA (Colegio Federado de Ingenieros y de Arquitectos): "Tabla de Valores Unitarios por Tipo de Obra" (Promedios 2024-2025).
A31: Ministerio de Hacienda: Manual de Valores Base Unitarios por Tipología Constructiva (Órgano de Normalización Técnica - ONT).
A32: SICOP (Sistema Integrado de Compras Públicas): Análisis de precios adjudicados recientes para Escuelas Tipo y EBAIS/Clínicas de la CCSS.
A33: 2. Infraestructura Vial (Transporte):
A34: MOPT / CONAVI: Precios promedio de licitación para obras de rehabilitación y recarpeteo asfáltico.
A35: LanammeUCR: Informes de costos de mantenimiento de la Red Vial Nacional.
A37: > Nota: Estos costos son referenciales, incluyen costos directos e indirectos, pero excluyen el valor del terreno.

Sheet Intervenciones
A2: Herramienta de Evaluación de Costo-Beneficio de Intervenciones para la Reducción de Riesgo Catastrófico
A6: Intervenciones
B8: Campo editable
A11: Sector | B11: Intervención | C11: Descripción | D11: Factor_Costo | E11: Factor_Beneficio
A12: Educación | B12: Mantenimiento Correctivo Menor | C12: Reparación de techos/cielos y sistemas eléctricos | D12: 0.05 | E12: 0.2
A13: Educación | B13: Reforzamiento Estructural (Retrofitting) | C13: Refuerzo de sistema estructural según código sísmico | D13: 0.35 | E13: 0.7
A14: Educación | B14: Reconstrucción Total (Código Actual) | C14: Demolición y construcción nueva bajo código vigente | D14: 1.1 | E14: 1
A15: Residencial | B15: Mejora de Techos y Drenajes | C15: Reparación de cubiertas y bajantes | D15: 0.08 | E15: 0.25
A16: Residencial | B16: Reforzamiento de Sistema Estructural | C16: Refuerzo de sistema estructural según código sísmico | D16: 0.3 | E16: 0.7
A17: Residencial | B17: Reconstrucción (Vivienda Nueva) | C17: Demolición y construcción nueva bajo código vigente | D17: 1.1 | E17: 1
A18: Salud | B18: Reforzamiento No Estructural | C18: Aseguramiento de equipos/cielos/fachadas | D18: 0.1 | E18: 0.3
A19: Salud | B19: Reforzamiento Estructural Integral | C19: Refuerzo completo para seguridad de la vida y operación | D19: 0.4 | E19: 0.85
A20: Salud | B20: Reconstrucción Hospitalaria | C20: Nueva edificación de alta complejidad | D20: 1.2 | E20: 1
A21: Transporte | B21: Estabilización de Taludes | C21: Muros de contención y anclajes en puntos críticos | D21: 0.15 | E21: 0.4
A22: Transporte | B22: Mejora de Sistemas de Drenaje | C22: Ampliación de alcantarillas y cunetas | D22: 0.1 | E22: 0.3
A23: Transporte | B23: Rehabilitación Mayor (Recarpeteo) | C23: Sustitución de base y carpeta asfáltica/concreto | D23: 0.45 | E23: 0.7
A26: Notas | B26: Estos costos son de referencia, basados en valores típicos de construcción en Costa Rica para el 2025

Sheet Listas
A1: Sectores | B1: Provincias | C1: Cantones | J1: Vulnerabilidad | K1: Beneficio social
C2: Alajuela | D2: Cartago | E2: Guanacaste | F2: Heredia | G2: Limón | H2: Puntarenas | I2: San_Jose | K2: Tasa beneficio social | L2: Conversión $-kgCO2 | M2: Costo social tonCO2
A3: Educación | B3: Alajuela | C3: Alajuela | D3: Alvarado | E3: Abangares | F3: Alajuela | G3: Guácimo | H3: Abangares | I3: Acosta | J3: Alta | K3: 0.0831 | L3: 1 | M3: 40
A4: Residencial | B4: Cartago | C4: Atenas | D4: Cartago | E4: Bagaces | F4: Barva | G4: Limón | H4: Buenos_Aires | I4: Alajuela | J4: Promedio
A5: Salud | B5: Guanacaste | C5: Bagaces | D5: Curridabat | E5: Carrillo | F5: Belén | G5: Matina | H5: Corredores | I5: Alajuelita | J5: Baja
A6: Transporte | B6: Heredia | C6: Belén | D6: Desamparados | E6: Cañas | F6: Flores | G6: Pococí | H6: Coto_Brus | I6: Aserrí
B7: Limón | C7: Esparza | D7: Dota | E7: Guatuso | F7: Heredia | G7: Sarapiquí | H7: Esparza | I7: Cartago
B8: Puntarenas | C8: Garabito | D8: El_Guarco | E8: Hojancha | F8: Moravia | G8: Siquirres | H8: Garabito | I8: Curridabat
B9: San_Jose | C9: Grecia | D9: Jiménez | E9: La_Cruz | F9: Pococí | G9: Talamanca | H9: Golfito | I9: Desamparados
C10: Guatuso | D10: La_Unión | E10: Liberia | F10: San_Isidro | G10: Turrialba | H10: Montes_de_Oro | I10: Dota
C11: Heredia | D11: Oreamuno | E11: Nandayure | F11: San_José | G11: Vázquez_de_Coronado | H11: Nandayure | I11: El_Guarco
C12: La_Cruz | D12: Paraíso | E12: Nicoya | F12: San_Pablo | H12: Orotina | I12: Escazú
C13: Liberia | D13: Pérez_Zeledón | E13: Puntarenas | F13: San_Rafael | H13: Osa | I13: Garabito
C14: Los_Chiles | D14: San_José | E14: Santa_Cruz | F14: Santa_Bárbara | H14: Parrita | I14: Goicoechea
C15: Mora | D15: Siquirres | E15: Tilarán | F15: Santo_Domingo | H15: Puntarenas | I15: Grecia
C16: Naranjo | D16: Turrialba | E16: Upala | F16: Sarapiquí | H16: Pérez_Zeledón | I16: Heredia
C17: Orotina | D17: Vázquez_de_Coronado | F17: Tibás | H17: Quepos | I17: La_Unión
C18: Palmares | H18: San_José | I18: León_Cortés_Castro
C19: Poás | H19: San_Ramón | I19: Montes_de_Oca
C20: Río_Cuarto | H20: Tilarán | I20: Mora
C21: San_Carlos | I21: Moravia
C22: San_José | I22: Osa
C23: San_Mateo | I23: Paraíso
C24: San_Ramón | I24: Parrita
C25: Santa_Ana | I25: Puriscal
C26: Santa_Bárbara | I26: Pérez_Zeledón
C27: Sarapiquí | I27: Quepos
C28: Sarchí | I28: San_Isidro
C29: Tilarán | I29: San_José
C30: Turrubares | I30: San_Ramón
C31: Upala | I31: Santa_Ana
C32: Zarcero | I32: Santo_Domingo
I33: Tarrazú
I34: Tibás
I35: Turrialba
I36: Turrubares
I37: Vázquez_de_Coronado
A44: Referencias
A45: Datos estadísticos de pérdidas | C45: Marco Global de Evaluación del Riesgo (GRAF), CNE UNDRR (2023)
A46: Beneficios sociales | C46: Precios Sociales en Costa Rica, MIDEPLAN (2025)

Sheet asset_counts_canton
A1: canton | B1: Acueductos | C1: Educación | D1: Energía | E1: Residencial | F1: Salud | G1: Transporte
A2: Abangares | B2: 56 | C2: 43 | D2: 0 | E2: 7932 | F2: 3 | G2: 18
A3: Acosta | B3: 245 | C3: 57 | D3: 0 | E3: 9028 | F3: 4 | G3: 8
A4: Alajuela | B4: 1370 | C4: 106 | D4: 3711 | E4: 110803 | F4: 32 | G4: 55
A5: Alajuelita | B5: 4237 | C5: 22 | D5: 2043 | E5: 25233 | F5: 5 | G5: 8
A6: Alvarado | B6: 0 | C6: 14 | D6: 0 | E6: 5612 | F6: 3 | G6: 11
A7: Aserrí | B7: 179 | C7: 33 | D7: 1212 | E7: 21236 | F7: 7 | G7: 10
A8: Atenas | B8: 330 | C8: 24 | D8: 0 | E8: 11835 | F8: 5 | G8: 13
A9: Bagaces | B9: 253 | C9: 33 | D9: 257 | E9: 9154 | F9: 4 | G9: 10
A10: Barva | B10: 1349 | C10: 19 | D10: 7313 | E10: 15340 | F10: 7 | G10: 8
A11: Belén | B11: 44 | C11: 6 | D11: 2750 | E11: 7311 | F11: 4 | G11: 8
A12: Buenos_Aires | B12: 446 | C12: 185 | D12: 0 | E12: 18612 | F12: 9 | G12: 15
A13: Carrillo | B13: 991 | C13: 35 | D13: 0 | E13: 17625 | F13: 6 | G13: 20
... A83: Zarcero | B83: 0 | C83: 20 | D83: 0 | E83: 4332 | F83: 3 | G83: 5

Sheet average_aalr_tot_canton
A1: canton | B1: Acueductos | C1: Educación | D1: Energía | E1: Residencial | F1: Salud | G1: Transporte
A2: Abangares | B2: 0.0058538462 | C2: 0.012623256 | D2: 0 | E2: 0.0025723399 | F2: 0.015733333 | G2: 0.00286
A3: Acosta | B3: 0.0056875 | C3: 0.014487719 | D3: 0 | E3: 0.0037337506 | F3: 0.03905 | G3: 0.004425
A4: Alajuela | B4: 0.0092364583 | C4: 0.016333019 | D4: 0.0065666667 | E4: 0.0032682987 | F4: 0.039515625 | G4: 0.0034073171
A5: Alajuelita | B5: 0.0064826087 | C5: 0.019113636 | D5: 0.0118 | E5: 0.0039215274 | F5: 0.0386 | G5: 0.0033125
A6: Alvarado | B6: 0 | C6: 0.012185714 | D6: 0 | E6: 0.0028073949 | F6: 0.040533333 | G6: 0.0027
A7: Aserrí | B7: 0.00652 | C7: 0.015339394 | E7: 0.0036082549 | F7: 0.042728571 | G7: 0.00347
A8: Atenas | B8: 0.0073766667 | C8: 0.015804167 | D8: 0 | E8: 0.0035123954 | F8: 0.04108 | G8: 0.0038166667
A9: Bagaces | B9: 0.013825 | C9: 0.0138 | E9: 0.0028223837 | F9: 0.033225 | G9: 0.003375
A10: Barva | C10: 0.012136842 | D10: 0.006 | E10: 0.0032772947 | F10: 0.045871429 | G10: 0.003075
A11: Belén | B11: 0.011290909 | C11: 0.020016667 | D11: 0.0118 | E11: 0.0039701272 | F11: 0.048575 | G11: 0.0037
A12: Buenos_Aires | B12: 0.0066758621 | C12: 0.011127027 | D12: 0 | E12: 0.0033420643 | F12: 0.0391 | G12: 0.0035714286
A13: Carrillo | B13: 0.011498667 | C13: 0.01602 | D13: 0 | E13: 0.0026742468 | F13: 0.046816667 | G13: 0.004605
A14: Cartago | B14: 0.0096363636 | C14: 0.015224324 | E14: 0.0031181126 | F14: 0.039341379 | G14: 0.0030791667
A15: Cañas | B15: 0.010639535 | C15: 0.013744737 | D15: 0 | E15: 0.0027917999 | F15: 0.0358 | G15: 0.0034444444
A16: Corredores | B16: 0.0066232558 | C16: 0.014478022 | D16: 0 | E16: 0.0037387456 | F16: 0.040471429 | G16: 0.0043416667
A17: Coto_Brus | B17: 0.0040840909 | C17: 0.010226087 | D17: 0 | E17: 0.0029356642 | F17: 0.034866667 | G17: 0.0025153846
A18: Curridabat | B18: 0.0063117647 | C18: 0.017526667 | D18: 0.0114 | E18: 0.0037422571 | F18: 0.041455556 | G18: 0.00315
A19: Desamparados | B19: 0.0078679245 | C19: 0.018639474 | D19: 0.0118 | E19: 0.0036805598 | F19: 0.03966087 | G19: 0.0033090909
A20: Dota | B20: 0 | C20: 0.012238462 | D20: 0 | E20: 0.0033820998 | F20: 0.04825 | G20: 0.0032666667
A21: El_Guarco | B21: 0.0075 | C21: 0.013859375 | D21: 0 | E21: 0.0031871719 | F21: 0.046133333 | G21: 0.0031666667
A22: Escazú | B22: 0.008298 | C22: 0.018828571 | D22: 0.012 | E22: 0.0038909075 | F22: 0.03892 | G22: 0.0033272727
A23: Esparza | B23: 0.0084928571 | C23: 0.015883333 | D23: 0 | E23: 0.0035063838 | F23: 0.044442857 | G23: 0.0036666667
A24: Flores | C24: 0.016816667 | E24: 0.003363689 | F24: 0.0017 | G24: 0.00325
A25: Garabito | B25: 0.01273125 | C25: 0.017631579 | D25: 0 | E25: 0.0038735063 | F25: 0.0364 | G25: 0.0038333333
A26: Goicoechea | B26: 0.0093529412 | C26: 0.017082759 | D26: 0.0113 | E26: 0.0033819665 | F26: 0.03718 | G26: 0.0031235294
A27: Golfito | B27: 0.0071724138 | C27: 0.014428431 | D27: 0 | E27: 0.0037969787 | F27: 0.040555556 | G27: 0.0044733333
A28: Grecia | C28: 0.014084783 | D28: 0.0032 | E28: 0.0033396648 | F28: 0.040869231 | G28: 0.0033769231
A29: Guatuso | B29: 0 | C29: 0.0095321429 | D29: 0.0041 | E29: 0.002357776 | F29: 0.0254 | G29: 0.0026
A30: Guácimo | B30: 0.0051538462 | C30: 0.006512069 | D30: 0 | E30: 0.001823314 | F30: 0.0190125 | G30: 0.0015555556
A31: Heredia | B31: 0.0085 | C31: 0.017407143 | D31: 0.0012055556 | E31: 0.0033606572 | F31: 0.02452 | G31: 0.00317
A32: Hojancha | B32: 0.006775 | C32: 0.010745455 | D32: 0 | E32: 0.0019094386 | F32: 0.0203 | G32: 0.0027
A33: Jiménez | B33: 0 | C33: 0.010366667 | D33: 0 | E33: 0.0026200563 | F33: 0.039166667 | G33: 0.0026
A34: La_Cruz | B34: 0.0085764706 | C34: 0.011380851 | D34: 0 | E34: 0.0022626602 | F34: 0.03704 | G34: 0.0033222222
A35: La_Unión | B35: 0.00775 | C35: 0.01725 | D35: 0.0112 | E35: 0.0032287023 | F35: 0.0399 | G35: 0.0031
A36: León_Cortés_Castro | B36: 0 | C36: 0.013558621 | D36: 0 | E36: 0.0034596765 | F36: 0.049866667 | G36: 0.00355
A37: Liberia | B37: 0.011129167 | C37: 0.017830435 | D37: 0 | E37: 0.0028278296 | F37: 0.037 | G37: 0.0036222222
A38: Limón | B38: 0.0039418605 | C38: 0.0046492857 | D38: 0 | E38: 0.00081340023 | F38: 0.0100875 | G38: 0.0011
A39: Los_Chiles | B39: 0.010668 | C39: 0.00918125 | D39: 0 | E39: 0.0054437636 | F39: 0.022885714 | G39: 0.0061230769
A40: Matina | B40: 0.0029708333 | C40: 0.0046037037 | D40: 0 | E40: 0.00129191 | F40: 0.012455556 | G40: 0.0033833333
... A42: Montes_de_Oro | B42: 0.01079 | C42: 0.014752632 | D42: 0.0051 | E42: 0.0031111283 | F42: 0.0019 | G42: 0.00344
A43: Mora | B43: 0.0080314286 | C43: 0.014988 | E43: 0.0036776422 | F43: 0.034633333 | G43: 0.0036666667
A44: Moravia | B44: 0.011066667 | C44: 0.01618125 | E44: 0.0034244667 | F44: 0.016033333 | G44: 0.0030571429
A45: Nandayure | B45: 0 | C45: 0.010781633 | D45: 0 | E45: 0.0017921919 | F45: 0.03055 | G45: 0.0028117647
A46: Naranjo | C46: 0.014341176 | D46: 0 | E46: 0.0032791976 | F46: 0.03485 | G46: 0.0033541667
A47: Nicoya | B47: 0.007527027 | C47: 0.011558182 | D47: 0 | E47: 0.0018207396 | F47: 0.034853846 | G47: 0.0027433333
A48: Oreamuno | B48: 0 | C48: 0.013755 | D48: 0 | E48: 0.0030231818 | F48: 0.03466 | G48: 0.00287
A49: Orotina | B49: 0.0099612903 | C49: 0.017215789 | D49: 0 | E49: 0.0035813672 | F49: 0.036466667 | G49: 0.0046142857
A50: Osa | B50: 0.0089107143 | C50: 0.013990099 | D50: 0 | E50: 0.0052146934 | F50: 0.045 | G50: 0.0067166667
A51: Palmares | B51: 0.0082956522 | C51: 0.016152941 | D51: 0 | E51: 0.0033317171 | F51: 0.0434 | G51: 0.00351
A52: Paraíso | B52: 0 | C52: 0.0137925 | D52: 0 | E52: 0.0030994961 | F52: 0.038371429 | G52: 0.0037882353
A53: Parrita | B53: 0.00981 | C53: 0.016866667 | D53: 0 | E53: 0.0049915948 | F53: 0.0279 | G53: 0.0069555556
A54: Pococí | B54: 0.0059117647 | C54: 0.006263522 | D54: 0 | E54: 0.0019476444 | F54: 0.02129 | G54: 0.0017111111
A55: Poás | B55: 0.0095 | C55: 0.01391 | D55: 0.003 | E55: 0.0031697315 | F55: 0.0397 | G55: 0.00325
A56: Puntarenas | B56: 0.0088235294 | C56: 0.013283799 | E56: 0.0027321373 | F56: 0.033412 | G56: 0.0030705882
A57: Puriscal | B57: 0.0084367647 | C57: 0.015328767 | D57: 0 | E57: 0.0036580228 | F57: 0.044783333 | G57: 0.0038125
A58: Pérez_Zeledón | B58: 0.0060847059 | C58: 0.012418852 | D58: 0 | E58: 0.003365127 | F58: 0.0426 | G58: 0.0032121951
A59: Quepos | B59: 0.008252 | C59: 0.013955319 | D59: 0 | E59: 0.0037860115 | F59: 0.036366667 | G59: 0.00435
A60: Río_Cuarto | B60: 0 | C60: 0.0086363636 | D60: 0 | E60: 0.0023857378 | F60: 0.0365 | G60: 0.00232
A61: San_Carlos | B61: 0 | C61: 0.010243985 | D61: 0.0049 | E61: 0.0031072038 | F61: 0.030124242 | G61: 0.0034111111
A62: San_Isidro | C62: 0.012983333 | D62: 0.0006 | E62: 0.003323192 | F62: 0.0341 | G62: 0.003
A63: San_José | B63: 0.0082363636 | C63: 0.016592381 | D63: 0.011314286 | E63: 0.0042509569 | F63: 0.013146875 | G63: 0.0032673469
A64: San_Mateo | B64: 0.011353333 | C64: 0.014321429 | D64: 0 | E64: 0.0036680291 | F64: 0.05345 | G64: 0.0037666667
A65: San_Pablo | B65: 0.011353333 | C65: 0.016883333 | D65: 0.0006 | E65: 0.0033728561 | F65: 0.035175 | G65: 0.0031
A66: San_Rafael | B66: 0.00765 | C66: 0.01406 | D66: 0.0006 | E66: 0.0033545081 | F66: 0.034325 | G66: 0.00305
A67: San_Ramón | B67: 0.0082365385 | C67: 0.013552 | D67: 0.0049 | E67: 0.0032595161 | F67: 0.0424375 | G67: 0.0033230769
A68: Santa_Ana | B68: 0.01025 | C68: 0.017022222 | D68: 0.0116 | E68: 0.0041049281 | F68: 0.041083333 | G68: 0.0035454545
A69: Santa_Bárbara | B69: 0 | C69: 0.0165 | D69: 0.0117 | E69: 0.0032493754 | F69: 0.0405625 | G69: 0.0031375
A70: Santa_Cruz | B70: 0.0085448598 | C70: 0.013735366 | D70: 0 | E70: 0.002275142 | F70: 0.047066667 | G70: 0.0032962963
A71: Santo_Domingo | B71: 0.0085 | C71: 0.015335294 | D71: 0.0112 | E71: 0.0033950686 | F71: 0.039528571 | G71: 0.0030818182
A72: Sarapiquí | B72: 0 | C72: 0.0083524194 | D72: 0 | E72: 0.0024562233 | F72: 0.0227 | G72: 0.0031947368
A73: Sarchí | B73: 0 | C73: 0.01445 | D73: 0 | E73: 0.0032776431 | F73: 0.035675 | G73: 0.0031857143
A74: Siquirres | B74: 0.00548 | C74: 0.0065020833 | D74: 0 | E74: 0.0019923728 | F74: 0.018542857 | G74: 0.0029666667
... A77: Tibás | B77: 0.0092 | C77: 0.017170588 | D77: 0.0115 | E77: 0.003960515 | F77: 0.0169 | G77: 0.00319
A78: Tilarán | B78: 0.0057972222 | C78: 0.012278261 | E78: 0.0025945866 | F78: 0.03408 | G78: 0.0027315789
A79: Turrialba | B79: 0 | C79: 0.0084541401 | D79: 0 | E79: 0.0022574559 | F79: 0.029392857 | G79: 0.002255
A80: Turrubares | B80: 0.0049933333 | C80: 0.015327273 | D80: 0 | E80: 0.0038919415 | F80: 0.0531 | G80: 0.0045666667
A81: Upala | B81: 0 | C81: 0.010797727 | D81: 0.0026 | E81: 0.0032749641 | F81: 0.032707692 | G81: 0.0030086957
A82: Vázquez_de_Coronado | B82: 0.0046757576 | C82: 0.015327778 | D82: 0.0109 | E82: 0.0032466527 | F82: 0.02215 | G82: 0.0030125
A83: Zarcero | B83: 0 | C83: 0.01251 | D83: 0 | E83: 0.003193675 | F83: 0.031233333 | G83: 0.0031

Sheet std_dev_aalr_tot_canton
A1: canton | B1: Acueductos | C1: Educación | D1: Energía | E1: Residencial | F1: Salud | G1: Transporte
A2: Abangares | B2: 0.0026468898 | C2: 0.0034004087 | D2: 0 | E2: 0.0021067493 | F2: 0.024566305 | G2: 0.00015776213
A3: Acosta | B3: 0.0026497436 | C3: 0.0030651888 | D3: 0 | E3: 0.0031014404 | F3: 0.024788909 | G3: 0.0021332403
A4: Alajuela | B4: 0.0051922639 | C4: 0.0065450195 | D4: 0.0020428738 | E4: 0.0022191468 | F4: 0.01851615 | G4: 0.00053309954
A5: Alajuelita | B5: 0.0072923155 | C5: 0.0071854546 | E5: 0.0076524775 | F5: 0.020627894 | G5: 3.5355339e-05
A6: Alvarado | B6: 0 | C6: 0.0044420815 | D6: 0 | E6: 0.0020700323 | F6: 0.00073711148 | G6: 0.00033763886
A7: Aserrí | B7: 0.004400707 | C7: 0.0051124199 | E7: 0.0035722276 | F7: 0.018121784 | G7: 0.00012516656
A8: Atenas | B8: 0.0031381615 | C8: 0.0050588261 | D8: 0 | E8: 0.0026270037 | F8: 0.021902785 | G8: 0.00038098755
A9: Bagaces | B9: 0.01175938 | C9: 0.0048561173 | E9: 0.0027066691 | F9: 0.021070892 | G9: 0.001190138
A10: Barva | C10: 0.00033864194 | D10: 0.0076367532 | E10: 0.0023614524 | F10: 0.00042314019 | G10: 7.0710678e-05
A11: Belén | B11: 0.0011292261 | C11: 0.007688021 | E11: 0.0026810389 | F11: 0.00026299556 | G11: 0.00060827625
A12: Buenos_Aires | B12: 0.0086433151 | C12: 0.0025312019 | D12: 0 | E12: 0.0037212669 | F12: 0.014242454 | G12: 0.002220682
A13: Carrillo | B13: 0.0041025863 | C13: 0.0065428362 | D13: 0 | E13: 0.0028383637 | F13: 0.022646803 | G13: 0.0018394722
A14: Cartago | B14: 0.010031453 | C14: 0.0058693728 | E14: 0.0021907671 | F14: 0.015404557 | G14: 0.0001718927
A15: Cañas | B15: 0.0085416665 | C15: 0.0050270994 | D15: 0 | E15: 0.0022600016 | F15: 0.022975349 | G15: 0.0010584318
A16: Corredores | B16: 0.0029243507 | C16: 0.0043378387 | D16: 0 | E16: 0.004884546 | F16: 0.028327649 | G16: 0.0025119563
A17: Coto_Brus | B17: 0.0017543227 | C17: 0.0018744865 | D17: 0 | E17: 0.0023844233 | F17: 0.015927639 | G17: 0.0001724633
A18: Curridabat | B18: 0.0026131596 | C18: 0.0069599329 | E18: 0.0042992611 | F18: 0.014910576 | G18: 5.4772256e-05
A19: Desamparados | B19: 0.0073605438 | C19: 0.0069607678 | D19: 0.00014142136 | E19: 0.0054241098 | F19: 0.017821762 | G19: 8.1117733e-05
A20: Dota | B20: 0 | C20: 0.00037757662 | D20: 0 | E20: 0.0034020507 | F20: 0.00049497475 | G20: 5.7735027e-05
A21: El_Guarco | B21: 0.0068873245 | C21: 0.0044279071 | D21: 0 | E21: 0.0022656687 | F21: 0.00060277138 | G21: 0.00011547005
A22: Escazú | B22: 0.0062896575 | C22: 0.0073659746 | E22: 0.0048632589 | F22: 0.020751193 | G22: 4.6709937e-05
A23: Esparza | B23: 0.0031414748 | C23: 0.0050726437 | D23: 0 | E23: 0.0027897226 | F23: 0.018756053 | G23: 0.0001118034
A24: Flores | C24: 0.007390106 | E24: 0.002346415 | G24: 5.7735027e-05
A25: Garabito | B25: 0.0075557235 | C25: 0.0062859679 | D25: 0 | E25: 0.0059160338 | F25: 0.029705723 | G25: 5.7735027e-05
A26: Goicoechea | B26: 0.011611908 | C26: 0.0065861364 | E26: 0.0038915241 | F26: 0.018708156 | G26: 9.0342486e-05
A27: Golfito | B27: 0.0023211599 | C27: 0.0036021275 | D27: 0 | E27: 0.0054553243 | F27: 0.02238633 | G27: 0.0037024059
A28: Grecia | C28: 0.0040667742 | E28: 0.002415372 | F28: 0.01737548 | G28: 0.00012351684
A29: Guatuso | B29: 0 | C29: 0.0025690541 | E29: 0.0019704149 | F29: 0.016166426 | G29: 0.00094566681
A30: Guácimo | B30: 0.0015446765 | C30: 0.0018558658 | D30: 0 | E30: 0.0014234655 | F30: 0.0080056119 | G30: 0.0003503966
A31: Heredia | B31: 0.0019407902 | C31: 0.0069248719 | D31: 0.0025691546 | E31: 0.0022474682 | F31: 0.024055528 | G31: 8.232726e-05
A32: Hojancha | B32: 0.0023171462 | C32: 0.00027207715 | D32: 0 | E32: 0.0020791638 | F32: 0.026587215 | G32: 0
A33: Jiménez | B33: 0 | C33: 0.00098556245 | D33: 0 | E33: 0.0020895714 | F33: 0.00058594653 | G33: 0.00023094011
A34: La_Cruz | B34: 0.0028342833 | C34: 0.001339474 | D34: 0 | E34: 0.0019328236 | F34: 0.02061269 | G34: 0.0003929942
A35: La_Unión | B35: 0.0069628637 | C35: 0.0068007897 | E35: 0.0021349206 | F35: 0.015557038 | G35: 0
A36: León_Cortés_Castro | B36: 0 | C36: 0.0025849174 | D36: 0 | E36: 0.0029171425 | F36: 0.001123981 | G36: 8.3666003e-05
A37: Liberia | B37: 0.0077969432 | C37: 0.0080285288 | D37: 0 | E37: 0.0022437778 | F37: 0.027302454 | G37: 0.00033082389
A38: Limón | B38: 0.0060806576 | C38: 0.0025843607 | D38: 0 | E38: 0.0021406702 | F38: 0.0044777785 | G38: 0.0018032378
A39: Los_Chiles | B39: 0.0089912328 | C39: 0.0033818239 | D39: 0 | E39: 0.006140777 | F39: 0.014893223 | G39: 0.0040682006
A40: Matina | B40: 0.001732673 | C40: 0.0024946708 | D40: 0 | E40: 0.0027113001 | F40: 0.0047034857 | G40: 0.0033378908
A41: Montes_de_Oca | C41: 0.0054557882 | E41: 0.0055343013 | F41: 0.015744925 | G41: 5.3452248e-05
A42: Montes_de_Oro | B42: 0.0099517112 | C42: 0.005034588 | E42: 0.0022885467 | G42: 8.9442719e-05
A43: Mora | B43: 0.0059511132 | C43: 0.0039749549 | E43: 0.0026018856 | F43: 0.028261694 | G43: 0.00013662601
A44: Moravia | B44: 0.011824229 | C44: 0.0063865712 | E44: 0.0025228275 | F44: 0.024826062 | G44: 7.8679579e-05
A45: Nandayure | B45: 0 | C45: 0.00027889176 | D45: 0 | E45: 0.0019717922 | F45: 0.019369478 | G45: 0.00037894979
A46: Naranjo | C46: 0.0041435688 | D46: 0 | E46: 0.0024039326 | F46: 0.022818621 | G46: 9.3153294e-05
A47: Nicoya | B47: 0.0058975569 | C47: 0.0033759914 | D47: 0 | E47: 0.0020120314 | F47: 0.014871876 | G47: 0.00032236554
A48: Oreamuno | B48: 0 | C48: 0.0053552213 | D48: 0 | E48: 0.0021259006 | F48: 0.0185144 | G48: 9.486833e-05
A49: Orotina | B49: 0.0028876377 | C49: 0.0059104675 | D49: 0 | E49: 0.0027125876 | F49: 0.029849009 | G49: 0.0014123604
A50: Osa | B50: 0.0066046751 | C50: 0.0037836888 | D50: 0 | E50: 0.0058937247 | F50: 0.025010887 | G50: 0.0036471242
A51: Palmares | B51: 0.0026349881 | C51: 0.005837178 | D51: 0 | E51: 0.0023836275 | F51: 0.018300091 | G51: 3.1622777e-05
A52: Paraíso | C52: 0.005050483 | D52: 0 | E52: 0.0024834855 | F52: 0.016424343 | G52: 0.0017659567
A53: Parrita | B53: 0.0073060105 | C53: 0.0044554359 | D53: 0 | E53: 0.0052583122 | F53: 0.03648671 | G53: 0.0039099588
A54: Pococí | B54: 0.0055497615 | C54: 0.0036136594 | D54: 0 | E54: 0.0026968177 | F54: 0.009869191 | G54: 0.00098501594
A55: Poás | C55: 0.0043155655 | E55: 0.0023363684 | F55: 0.018664083 | G55: 0.00011952286
A56: Puntarenas | B56: 0.0047922025 | C56: 0.0042657922 | E56: 0.0035495727 | F56: 0.020403193 | G56: 0.00026230841
A57: Puriscal | B57: 0.0048214664 | C57: 0.003172647 | D57: 0 | E57: 0.0027723061 | F57: 0.021014987 | G57: 8.0622577e-05
A58: Pérez_Zeledón | B58: 0.0042100646 | C58: 0.0029956438 | D58: 0 | E58: 0.0030071367 | F58: 0.01452209 | G58: 0.00066790535
A59: Quepos | B59: 0.0039786011 | C59: 0.0007549283 | D59: 0 | E59: 0.0047025962 | F59: 0.02669799 | G59: 0.0017658077
A60: Río_Cuarto | B60: 0 | C60: 0.0015428932 | D60: 0 | E60: 0.0017416531 | F60: 0.0021213203 | G60: 0.0005432413
A61: San_Carlos | B61: 0 | C61: 0.0037903131 | E61: 0.0032508284 | F61: 0.016396132 | G61: 0.0023691642
A62: San_Isidro | C62: 0.0037980457 | D62: 0 | E62: 0.002340434 | F62: 0.021667487 | G62: 0
A63: San_José | B63: 0.0091234065 | C63: 0.0064766548 | D63: 0.0020095012 | E63: 0.0081610212 | F63: 0.020144846 | G63: 5.1590354e-05
A64: San_Mateo | B64: 0.0079249035 | C64: 0.00023916062 | D64: 0 | E64: 0.0027890904 | F64: 0.00035355339 | G64: 8.1649658e-05
A65: San_Pablo | B65: 0.009373966 | C65: 0.0068683089 | D65: 0 | E65: 0.0020702614 | F65: 0.022320002 | G65: 0
A66: San_Rafael | B66: 0.0025 | C66: 0.0046864242 | D66: 0 | E66: 0.0023528227 | F66: 0.02175046 | G66: 5.4772256e-05
A67: San_Ramón | B67: 0.0052222011 | C67: 0.0035687046 | E67: 0.0023398232 | F67: 0.016104487 | G67: 0.00029162674
A68: Santa_Ana | B68: 0.010975883 | C68: 0.0066455253 | D68: 0.0035679126 | E68: 0.0060583821 | F68: 0.019247485 | G68: 0.00032973819
A69: Santa_Bárbara | B69: 0 | C69: 0.0065490966 | E69: 0.0022803112 | F69: 0.015713228 | G69: 5.1754917e-05
A70: Santa_Cruz | B70: 0.0042179588 | C70: 0.0054639644 | D70: 0 | E70: 0.00261112 | F70: 0.018366682 | G70: 0.00039172349
A71: Santo_Domingo | B71: 0.0019714631 | C71: 0.0057908269 | E71: 0.0023123715 | F71: 0.016691087 | G71: 7.5075719e-05
A72: Sarapiquí | B72: 0 | C72: 0.0034872232 | D72: 0 | E72: 0.0034179949 | F72: 0.01081072 | G72: 0.002689377
A73: Sarchí | B73: 0 | C73: 0.0046888165 | D73: 0 | E73: 0.0024258436 | F73: 0.022613473 | G73: 0.00012149858
A74: Siquirres | B74: 0.008842624 | C74: 0.0023889209 | D74: 0 | E74: 0.0034217032 | F74: 0.0072080846 | G74: 0.0026532101
A75: Talamanca | B75: 0.0052065053 | C75: 0.0032429355 | D75: 0 | E75: 0.0048074903 | F75: 0.010339756 | G75: 0.0036095772
A76: Tarrazú | B76: 0 | C76: 0.0026294936 | D76: 0 | E76: 0.0037998774 | F76: 0.028324003 | G76: 8.3666003e-05
A77: Tibás | C77: 0.006648944 | E77: 0.0075568052 | F77: 0.026327172 | G77: 3.1622777e-05
A78: Tilarán | B78: 0.0024773818 | C78: 0.0038163923 | E78: 0.00196848 | F78: 0.018252726 | G78: 9.459053e-05
A79: Turrialba | B79: 0 | C79: 0.0022899583 | D79: 0 | E79: 0.0018140346 | F79: 0.012227803 | G79: 0.00037059696
A80: Turrubares | B80: 0.0042486076 | C80: 0.0013775596 | D80: 0 | E80: 0.0037164284 | G80: 0.0020650042
A81: Upala | B81: 0 | C81: 0.0026885811 | D81: 0 | E81: 0.0037631074 | F81: 0.014788704 | G81: 0.0013684474
A82: Vázquez_de_Coronado | B82: 0.0076606148 | C82: 0.0061784069 | E82: 0.0023127513 | F82: 0.029062089 | G82: 6.4086994e-05
A83: Zarcero | B83: 0 | C83: 0.00024473401 | D83: 0 | E83: 0.0023617256 | F83: 0.025576617 | G83: 0

Sheet min_aalr_tot_canton
A1: canton | B1: Acueductos | C1: Educación | D1: Energía | E1: Residencial | F1: Salud | G1: Transporte
A2: Abangares | B2: 0.0035 | C2: 0.0108 | E2: 0.0009 | F2: 0.0015 | G2: 0.0026
A3: Acosta | B3: 0.0044 | C3: 0.0127 | E3: 0.002 | F3: 0.0019 | G3: 0.0036
A4: Alajuela | B4: 0.0034 | C4: 0.0085 | D4: 0.0051 | E4: 0.0015 | F4: 0.0017 | G4: 0.0027
A5: Alajuelita | B5: 0.003 | C5: 0.012 | D5: 0.0118 | E5: 0.002 | F5: 0.0017 | G5: 0.0033
A6: Alvarado | C6: 0.0099 | E6: 0.0016 | F6: 0.0397 | G6: 0.0025
A7: Aserrí | B7: 0.0031 | C7: 0.0121 | E7: 0.002 | F7: 0.0017 | G7: 0.0033
A8: Atenas | B8: 0.0044 | C8: 0.0136 | E8: 0.0021 | F8: 0.0019 | G8: 0.0036
A9: Bagaces | B9: 0.004 | C9: 0.0109 | E9: 0.0011 | F9: 0.0017 | G9: 0.0028
A10: Barva | C10: 0.0114 | D10: 0.0006 | E10: 0.0006 | F10: 0.0452 | G10: 0.003
A11: Belén | B11: 0.0094 | C11: 0.0129 | D11: 0.0118 | E11: 0.0021 | F11: 0.0483 | G11: 0.0033
A12: Buenos_Aires | B12: 0.0034 | C12: 0.0095 | E12: 0.0016 | F12: 0.0013 | G12: 0.0027
A13: Carrillo | B13: 0.0041 | C13: 0.0126 | E13: 0.0009 | F13: 0.0018 | G13: 0.0031
A14: Cartago | B14: 0.0027 | C14: 0.0107 | E14: 0.0019 | F14: 0.0016 | G14: 0.0029
A15: Cañas | B15: 0.0038 | C15: 0.0109 | E15: 0.0009 | F15: 0.0016 | G15: 0.0027
A16: Corredores | B16: 0.0033 | C16: 0.0103 | E16: 0.0015 | F16: 0.0015 | G16: 0.0025
A17: Coto_Brus | B17: 0.0026 | C17: 0.0074 | E17: 0.0013 | F17: 0.0013 | G17: 0.0021
A18: Curridabat | B18: 0.0039 | C18: 0.0114 | D18: 0.0114 | E18: 0.002 | F18: 0.0017 | G18: 0.0031
A19: Desamparados | B19: 0.0028 | C19: 0.0117 | D19: 0.0117 | E19: 0.0019 | F19: 0.0017 | G19: 0.0032
A20: Dota | C20: 0.0118 | E20: 0.0019 | F20: 0.0479 | G20: 0.0032
A21: El_Guarco | B21: 0.0038 | C21: 0.0116 | E21: 0.0018 | F21: 0.0455 | G21: 0.0031
A22: Escazú | B22: 0.003 | C22: 0.0121 | D22: 0.012 | E22: 0.002 | F22: 0.0018 | G22: 0.0033
A23: Esparza | B23: 0.0042 | C23: 0.0133 | E23: 0.0017 | F23: 0.002 | G23: 0.0035
A24: Flores | C24: 0.0118 | E24: 0.002 | F24: 0.0017 | G24: 0.0032
A25: Garabito | B25: 0.0048 | C25: 0.0138 | E25: 0.0018 | F25: 0.0021 | G25: 0.0038
A26: Goicoechea | B26: 0.0028 | C26: 0.0113 | D26: 0.0113 | E26: 0.0019 | F26: 0.0017 | G26: 0.0029
A27: Golfito | B27: 0.0026 | C27: 0.0114 | E27: 0.0013 | F27: 0.0015 | G27: 0.0026
A28: Grecia | C28: 0.012 | D28: 0.0032 | E28: 0.0019 | F28: 0.0018 | G28: 0.0032
A29: Guatuso | C29: 0.0077 | D29: 0.0041 | E29: 0.001 | F29: 0.0012 | G29: 0.0019
A30: Guácimo | B30: 0.0023 | C30: 0.0039 | E30: 0.0004 | F30: 0.001 | G30: 0.0012
A31: Heredia | B31: 0.0041 | C31: 0.0116 | D31: 0.0006 | E31: 0.0006 | F31: 0.0017 | G31: 0.003
A32: Hojancha | B32: 0.0033 | C32: 0.0101 | E32: 0.0008 | F32: 0.0015 | G32: 0.0027
A33: Jiménez | C33: 0.0093 | E33: 0.0015 | F33: 0.0385 | G33: 0.0024
A34: La_Cruz | B34: 0.0042 | C34: 0.0092 | E34: 0.0008 | F34: 0.0017 | G34: 0.0026
A35: La_Unión | B35: 0.0038 | C35: 0.0113 | D35: 0.0112 | E35: 0.0019 | F35: 0.0016 | G35: 0.0031
A36: León_Cortés_Castro | C36: 0.0123 | E36: 0.002 | F36: 0.0489 | G36: 0.0035
A37: Liberia | B37: 0.0053 | C37: 0.0126 | E37: 0.0015 | F37: 0.0018 | G37: 0.0031
A38: Limón | B38: 0.0006 | C38: 0.0024 | E38: 0.0003 | F38: 0.0003 | G38: 0.0005
A39: Los_Chiles | B39: 0.0022 | C39: 0.0036 | E39: 0.0003 | F39: 0.0033 | G39: 0.0015
A40: Matina | B40: 0.0009 | C40: 0.0022 | E40: 0.0002 | F40: 0.0004 | G40: 0.0005
A41: Montes_de_Oca | B41: 0.0039 | C41: 0.0114 | D41: 0.0113 | E41: 0.002 | F41: 0.0017 | G41: 0.0031
A42: Montes_de_Oro | B42: 0.0042 | C42: 0.0126 | D42: 0.0051 | E42: 0.0018 | F42: 0.0019 | G42: 0.0033
A43: Mora | B43: 0.0032 | C43: 0.0135 | E43: 0.0021 | F43: 0.002 | G43: 0.0035
A44: Moravia | B44: 0.0028 | C44: 0.0113 | E44: 0.0019 | F44: 0.0017 | G44: 0.0029
A45: Nandayure | C45: 0.0102 | E45: 0.0008 | F45: 0.0015 | G45: 0.0026
A46: Naranjo | C46: 0.0122 | E46: 0.0019 | F46: 0.0018 | G46: 0.0032
A47: Nicoya | B47: 0.0033 | C47: 0.0096 | E47: 0.0008 | F47: 0.0015 | G47: 0.0026
A48: Oreamuno | C48: 0.0105 | E48: 0.0018 | F48: 0.0016 | G48: 0.0027
A49: Orotina | B49: 0.0046 | C49: 0.0146 | E49: 0.0018 | F49: 0.002 | G49: 0.0038
A50: Osa | B50: 0.004 | C50: 0.0111 | E50: 0.0013 | F50: 0.0041 | G50: 0.0027
A51: Palmares | B51: 0.0044 | C51: 0.0126 | E51: 0.0021 | F51: 0.0019 | G51: 0.0035
A52: Paraíso | C52: 0.0101 | E52: 0.0016 | F52: 0.0015 | G52: 0.0027
A53: Parrita | B53: 0.0048 | C53: 0.0141 | E53: 0.0018 | F53: 0.0021 | G53: 0.0038
A54: Pococí | B54: 0.0023 | C54: 0.0017 | E54: 0.0001 | F54: 0.0006 | G54: 0.0004
A55: Poás | B55: 0.0095 | C55: 0.0118 | D55: 0.003 | E55: 0.0019 | F55: 0.0017 | G55: 0.0031
A56: Puntarenas | B56: 0.0032 | C56: 0.0105 | E56: 0.0008 | F56: 0.0016 | G56: 0.0026
A57: Puriscal | B57: 0.0033 | C57: 0.0133 | E57: 0.0019 | F57: 0.0019 | G57: 0.0037
A58: Pérez_Zeledón | B58: 0.0038 | C58: 0.0107 | E58: 0.0017 | F58: 0.0015 | G58: 0.0028
A59: Quepos | B59: 0.0046 | C59: 0.0128 | E59: 0.0019 | F59: 0.0019 | G59: 0.0035
A60: Río_Cuarto | C60: 0.0047 | E60: 0.0003 | F60: 0.035 | G60: 0.0011
A61: San_Carlos | C61: 0.0023 | D61: 0.0049 | E61: 0.0001 | F61: 0.0011 | G61: 0.0009
A62: San_Isidro | C62: 0.0112 | D62: 0.0006 | E62: 0.0006 | F62: 0.0016 | G62: 0.003
A63: San_José | B63: 0.004 | C63: 0.0117 | D63: 0.0071 | E63: 0.002 | F63: 0.0017 | G63: 0.0032
A64: San_Mateo | B64: 0.0047 | C64: 0.0136 | E64: 0.002 | F64: 0.0532 | G64: 0.0037
A65: San_Pablo | B65: 0.0039 | C65: 0.0124 | D65: 0.0006 | E65: 0.0006 | F65: 0.0017 | G65: 0.0031
A66: San_Rafael | B66: 0.0039 | C66: 0.0121 | D66: 0.0006 | E66: 0.0006 | F66: 0.0017 | G66: 0.003
A67: San_Ramón | B67: 0.0042 | C67: 0.0104 | D67: 0.0049 | E67: 0.0016 | F67: 0.0018 | G67: 0.0026
A68: Santa_Ana | B68: 0.0031 | C68: 0.0123 | D68: 0.0077 | E68: 0.002 | F68: 0.0018 | G68: 0.0034
A69: Santa_Bárbara | C69: 0.0118 | D69: 0.0117 | E69: 0.0019 | F69: 0.0017 | G69: 0.0031
A70: Santa_Cruz | B70: 0.0036 | C70: 0.0099 | E70: 0.0008 | F70: 0.0016 | G70: 0.0027
A71: Santo_Domingo | B71: 0.0029 | C71: 0.0116 | D71: 0.0112 | E71: 0.0019 | F71: 0.0017 | G71: 0.003
A72: Sarapiquí | C72: 0.0021 | E72: 0.0001 | F72: 0.001 | G72: 0.001
A73: Sarchí | C73: 0.0121 | E73: 0.0019 | F73: 0.0018 | G73: 0.003
A74: Siquirres | B74: 0.0014 | C74: 0.0034 | E74: 0.0001 | F74: 0.0006 | G74: 0.001
A75: Talamanca | B75: 0.0007 | C75: 0.0026 | E75: 0.0003 | F75: 0.0004 | G75: 0.0005
A76: Tarrazú | C76: 0.0127 | E76: 0.002 | F76: 0.0017 | G76: 0.0034
A77: Tibás | B77: 0.0092 | C77: 0.0117 | D77: 0.0115 | E77: 0.002 | F77: 0.0017 | G77: 0.0031
A78: Tilarán | B78: 0.0026 | C78: 0.0106 | E78: 0.0015 | F78: 0.0015 | G78: 0.0026
A79: Turrialba | C79: 0.0039 | E79: 0.0003 | F79: 0.0012 | G79: 0.0015
A80: Turrubares | B80: 0.0035 | C80: 0.0144 | E80: 0.0018 | F80: 0.0531 | G80: 0.0037
A81: Upala | C81: 0.0076 | D81: 0.0026 | E81: 0.0009 | F81: 0.001 | G81: 0.0018
A82: Vázquez_de_Coronado | B82: 0.0027 | C82: 0.0111 | D82: 0.0109 | E82: 0.0018 | F82: 0.0016 | G82: 0.0029
A83: Zarcero | C83: 0.0118 | E83: 0.0019 | F83: 0.0017 | G83: 0.0031
